{
	"columns":[
		{
			"columnType":"STRING",
			"columnName":"pattern"
		},
		{
			"columnType":"STRING",
			"columnName":"sample_raw"
		},
		{
			"columnType":"STRING",
			"columnName":"sample_tmp"
		},
		{
			"columnType":"STRING",
			"columnName":"keywords"
		},
		{
			"columnType":"STRING",
			"columnName":"top_pattern"
		},
		{
			"columnType":"STRING",
			"columnName":"label_id"
		},
		{
			"columnType":"STRING",
			"columnName":"rec_label"
		},
		{
			"columnType":"STRING",
			"columnName":"groupby_label"
		},
		{
			"columnType":"BIGINT",
			"columnName":"gmt_create"
		},
		{
			"columnType":"STRING",
			"columnName":"sample"
		},
		{
			"columnType":"BIGINT",
			"columnName":"gmt_modified"
		},
		{
			"columnType":"BIGINT",
			"columnName":"config_id"
		},
		{
			"columnType":"PRIMARY KEY (`pattern`,`config_id`) NOT ENFORCED"
		}
	],
	"options":[
		{
			"value":"jdbc",
			"key":"connector"
		},
		{
			"value":"jdbc:mysql://{DB_HOST}:{DB_PORT}/{DB_NAME}?useUnicode=true&characterEncoding=utf-8&useSSL=false",
			"key":"url"
		},
		{
			"value":"{DB_ORIGIN_DATA_TABLE}",
			"key":"table-name"
		},
		{
			"value":"org.mariadb.jdbc.Driver",
			"key":"driver"
		},
		{
			"value":"{DB_PASSWD}",
			"key":"password"
		},
		{
			"value":"{DB_USER}",
			"key":"username"
		}
	],
	"sinkType":"jdbc"
}